matter/__init__.py
matter/android.py
matter/browser.py
matter/desktop.py
matter/http_utils.py
matter/matter_command.py
matter/mqtt.py
matter/socket.py
matter/annotations/__init__.py
matter/client/__init__.py
matter/client/adb.py
matter/client/adb_client_view.py
matter/client/browser.py
matter/client/desktop.py
matter/client/fake_utils.py
matter/client/http_utils.py
matter/client/mqtt_utils.py
matter/client/mumu.py
matter/client/socket_utils.py
matter/command/__init__.py
matter/command/record.py
matter/command/run_accept.py
matter/command/run_proxy.py
matter/command/uiautomatorviewer.py
matter/group/__init__.py
matter/manager/__init__.py
matter/manager/case_manager.py
matter/manager/client_manager.py
matter/manager/group_manager.py
matter/manager/proxy_manager.py
matter/manager/signal_manager.py
matter/mock/__init__.py
matter/proxy/__init__.py
matter/proxy/proxy_client.py
matter/proxy/proxy_server.py
matter/proxy/proxy_web_server.py
matter/record/__init__.py
matter/record/play_tools.py
matter/record/record_tools.py
matter/record/record_window.py
matter/service/matter_service.exe
matter/service/matter_service.xml
matter/utils/__init__.py
matter/utils/command.py
matter/utils/console.py
matter/utils/singleton.py
matter/utils/system_utils.py
matter_cli-2024.9.15.dist-info/LICENSE
matter_cli-2024.9.15.dist-info/METADATA
matter_cli-2024.9.15.dist-info/WHEEL
matter_cli-2024.9.15.dist-info/entry_points.txt
matter_cli-2024.9.15.dist-info/top_level.txt
matter_cli-2024.9.15.dist-info/RECORD
