Metadata-Version: 2.1
Name: matter-cli
Version: 2024.9.15
Summary: frame work for testing apps、website、products with one interface
Author-email: dan <dwdyoung0219@gmail.com>
License: GNU LESSER GENERAL PUBLIC LICENSE
Project-URL: Homepage, https://gitee.com/dwdyoung/matter
Project-URL: Issues, https://gitee.com/dwdyoung/matter/issues
Project-URL: Documentation, https://yuque/dengbuladuo/matter
Project-URL: Repository, https://gitee.com/dwdyoung/matter
Keywords: matter,test,autotest
Classifier: Programming Language :: Python :: 3
Classifier: License :: OSI Approved :: GNU Lesser General Public License v2 or later (LGPLv2+)
Classifier: Operating System :: OS Independent
Requires-Python: >=3.8
License-File: LICENSE
Requires-Dist: pyyaml
Requires-Dist: adbutils
Requires-Dist: androidviewclient
Requires-Dist: aapt
Requires-Dist: wget
Requires-Dist: selenium
Requires-Dist: pyautogui
Requires-Dist: Faker
Requires-Dist: opencv-python
Requires-Dist: numpy
Requires-Dist: lxml
Requires-Dist: bottle
Requires-Dist: pynput
Requires-Dist: click
